reformat_gherkin/__init__.py
reformat_gherkin/__main__.py
reformat_gherkin/ast_node/__init__.py
reformat_gherkin/ast_node/_base.py
reformat_gherkin/ast_node/background.py
reformat_gherkin/ast_node/comment.py
reformat_gherkin/ast_node/data_table.py
reformat_gherkin/ast_node/doc_string.py
reformat_gherkin/ast_node/examples.py
reformat_gherkin/ast_node/feature.py
reformat_gherkin/ast_node/gherkin_document.py
reformat_gherkin/ast_node/location.py
reformat_gherkin/ast_node/rule.py
reformat_gherkin/ast_node/scenario.py
reformat_gherkin/ast_node/step.py
reformat_gherkin/ast_node/table_cell.py
reformat_gherkin/ast_node/table_row.py
reformat_gherkin/ast_node/tag.py
reformat_gherkin/ast_node/tag_group.py
reformat_gherkin/cli.py
reformat_gherkin/config.py
reformat_gherkin/core.py
reformat_gherkin/errors.py
reformat_gherkin/formatter.py
reformat_gherkin/options.py
reformat_gherkin/parser.py
reformat_gherkin/report.py
reformat_gherkin/utils.py
reformat_gherkin/version.py
reformat_gherkin-3.0.0.dist-info/entry_points.txt
reformat_gherkin-3.0.0.dist-info/LICENSE
reformat_gherkin-3.0.0.dist-info/WHEEL
reformat_gherkin-3.0.0.dist-info/METADATA
reformat_gherkin-3.0.0.dist-info/RECORD
