Metadata-Version: 2.1
Name: reformat-gherkin
Version: 3.0.0
Summary: Formatter for Gherkin language
Home-page: https://github.com/ducminh-phan/reformat-gherkin
License: MIT
Author: Duc-Minh Phan
Author-email: alephvn@gmail.com
Requires-Python: >=3.7,<4.0
Classifier: Development Status :: 5 - Production/Stable
Classifier: Environment :: Console
Classifier: Intended Audience :: Developers
Classifier: License :: OSI Approved :: MIT License
Classifier: Operating System :: OS Independent
Classifier: Programming Language :: Python
Classifier: Programming Language :: Python :: 3
Classifier: Programming Language :: Python :: 3 :: Only
Classifier: Programming Language :: Python :: 3.10
Classifier: Programming Language :: Python :: 3.7
Classifier: Programming Language :: Python :: 3.8
Classifier: Programming Language :: Python :: 3.9
Classifier: Topic :: Software Development :: Quality Assurance
Requires-Dist: PyYAML (>=5.4)
Requires-Dist: attrs (>=20.2)
Requires-Dist: cattrs (>=1.1)
Requires-Dist: click (>=7)
Requires-Dist: gherkin-official (==24.0.0)
Requires-Dist: wcwidth (>=0.2.5,<0.3.0)
